{"skyUnite": {
    "rings": {
        "itemId": "3b62a91abc21df1a2609af53cb15d432",
        "itemName": "천계 연합군 : 모든 이를 위한 기도",
        "ispinsInfo": {
            "options": [
                {
                    "buff": 1405,
                    "explain": "물리, 마법 방어력 총 합이 90000 이상일 때 피해 증가 +7815\n\n물리, 마법 방어력 +14000\n\n피격 시 물리, 마법 방어력 -2800",
                    "explainDetail": "물리, 마법 방어력 총 합이 90000 이상일 때 피해 증가 +7815\n\n물리, 마법 방어력 +14000\n\n피격 시 물리, 마법 방어력 -2800 (최대 5중첩, 해당 옵션의 피격 판정은 총 HP 1% 이상 데미지를 받을 시에만 적용됩니다.)\n- 2초 동안 피격되지 않을 시 물리, 마법 방어력 감소 중첩수 1 감소"
                }
            ]
        }
    },
    "neck": {
        "itemId": "cb41d2e497f1a7ac1ae2711670da9861",
        "itemName": "천계 연합군 : 꺾이지 않는 의지",
        "ispinsInfo": {
            "options": [
                {
                    "buff": 1405,
                    "explain": "HP MAX, MP MAX 총 합이 220000 이상일 때 피해 증가 +7815\n\nHP MAX +1200, MP MAX +1890\n\n피격 시 HP MAX -240, MP MAX -378",
                    "explainDetail": "HP MAX, MP MAX 총 합이 220000 이상일 때 피해 증가 +7815\n\nHP MAX +1200, MP MAX +1890\n\n피격 시 HP MAX -240, MP MAX -378 (최대 5중첩, 해당 옵션의 피격 판정은 총 HP 1% 이상 데미지를 받을 시에만 적용됩니다.)\n- 2초 동안 피격되지 않을 시 HP MAX, MP MAX 감소 중첩수 1 감소"
                }
            ]
        }
    },
    "armlet": {
        "itemId": "f0683ab71a21f9166ccb3423fa0a928c",
        "itemName": "천계 연합군 : 밝게 빛나는 희망",
        "ispinsInfo": {
            "options": [
                {
                    "buff": 1405,
                    "explain": "모든 속성 저항 총 합이 100 이상일 때 피해 증가 +7815\n\n모든 속성 저항 +20\n\n피격 시 모든 속성 저항 -4",
                    "explainDetail": "모든 속성 저항 총 합이 100 이상일 때 피해 증가 +7815\n\n모든 속성 저항 +20\n\n피격 시 모든 속성 저항 -4 (최대 5중첩, 해당 옵션의 피격 판정은 총 HP 1% 이상 데미지를 받을 시에만 적용됩니다.)\n- 2초 동안 피격되지 않을 시 모든 속성 저항 감소 중첩수 1 감소"
                }
            ]
        }
    }
},
"goldDragon": {
    "rings": {
        "itemId": "52688ab6a97da9368e86343d0a3ac4a5",
        "itemName": "금룡 : 무한한 빛의 결계",
        "ispinsInfo": {
            "options": [
                {
                    "buff": 1405,
                    "explain": "공격 시 30% 확률로 랜덤한 효과 적용",
                    "explainDetail": "공격 시 30% 확률로 아래의 효과 3개 중 1개 효과 적용 (쿨타임 3초, 최대 1중첩, 적의 방어력과 상관없이 총 피해 증가 수치의 100%만큼 피해를 줌)\n- 200px 범위 내에 있는 랜덤한 적에게 테서랙트 붐을 1회 시전하며, 피해 증가 +7034\n- 300px 범위 내에 있는 랜덤한 적에게 테서랙트 붐을 최대 3회 시전하며, 피해 증가 +7815\n- 500px 범위 내에 있는 랜덤한 적에게 테서랙트 붐을 최대 5회 시전하며, 피해 증가 +8597"
                }
            ]
        }
    },
    "neck": {
        "itemId": "eeb469cdd183e41318837d2dbd98dd42",
        "itemName": "금룡 : 찬란한 용의 비늘",
        "ispinsInfo": {
            "options": [
                {
                    "buff": 1405,
                    "explain": "공격 시 30% 확률로 랜덤한 효과 적용",
                    "explainDetail": "공격 시 30% 확률로 아래의 효과 3개 중 1개 효과 적용 (쿨타임 3초, 최대 1중첩, 적의 방어력과 상관없이 총 피해 증가 수치의 100%만큼 피해를 줌)\n- 200px 범위 내에 있는 랜덤한 적에게 호리젠탈 큐브를 1회 시전하며, 피해 증가 +7034\n- 300px 범위 내에 있는 랜덤한 적에게 호리젠탈 큐브를 최대 3회 시전하며, 피해 증가 +7815\n- 500px 범위 내에 있는 랜덤한 적에게 호리젠탈 큐브를 최대 5회 시전하며, 피해 증가 +8597"
                }
            ]
        }
    },
    "armlet": {
        "itemId": "5285d14664a9aa41559ca68f440c3909",
        "itemName": "금룡 : 화려한 힘의 기원",
        "ispinsInfo": {
            "options": [
                {
                    "buff": 1405,
                    "explain": "공격 시 30% 확률로 랜덤한 효과 적용",
                    "explainDetail": "공격 시 30% 확률로 아래의 효과 3개 중 1개 효과 적용 (쿨타임 3초, 최대 1중첩, 적의 방어력과 상관없이 총 피해 증가 수치의 100%만큼 피해를 줌)\n- 200px 범위 내에 있는 랜덤한 적에게 버티컬 필러를 1회 시전하며, 피해 증가 +7034\n- 300px 범위 내에 있는 랜덤한 적에게 버티컬 필러를 최대 3회 시전하며, 피해 증가 +7815\n- 500px 범위 내에 있는 랜덤한 적에게 버티컬 필러를 최대 5회 시전하며, 피해 증가 +8597"
                }
            ]
        }
    }
},
"darkDragon": {
    "rings": {
        "itemId": "1fd082cd996a9eb02645be09c5e89d41",
        "itemName": "흑룡 : 끝없는 암흑의 굴레",
        "ispinsInfo": {
            "options": [
                {
                    "buff": 1518,
                    "explain": "피격 시 MP 5000 감소\n\n현재 MP 4% 마다 피해 증가 +1876\n\n스킬로 인해 소모한 MP 5000 마다 10초동안 장비로 인한 MP 회복 효과 10% 증가",
                    "explainDetail": "피격 시 MP 5000 감소 (쿨타임 0.5초, 해당 옵션의 피격 판정은 총 HP의 1% 이상 데미지를 받을 시에만 적용됩니다.)\n\n현재 MP 4% 마다 피해 증가 +1876 (최대 5중첩)\n\n스킬로 인해 소모한 MP 5000 마다 10초동안 장비로 인한 MP 회복 효과 10% 증가 (최대 1중첩)"
                }
            ]
        }
    },
    "neck": {
        "itemId": "db3a4579b25e7dbdca33f56195ce259f",
        "itemName": "흑룡 : 어두운 힘의 근본",
        "ispinsInfo": {
            "options": [
                {
                    "buff": 1518,
                    "explain": "스킬 시전 시 마나번 디버프가 발동하여 1초마다 MP 1% 감소\n\nMP가 50% 미만일 때 1초마다 MP 2% 회복",
                    "explainDetail": "스킬 시전 시 마나번 디버프가 발동하여 1초마다 MP 1% 감소 (최대 5중첩)\n- 마나번 디버프 중첩 수 1당 피해 증가 +1876\n\nMP가 50% 미만일 때 1초마다 MP 2% 회복\n- MP가 10% 감소할 때마다 1초마다 MP 1% 추가 회복"
                }
            ]
        }
    },
    "armlet": {
        "itemId": "27843216918f310d010f1014661c81bd",
        "itemName": "흑룡 : 주시하는 용의 눈동자",
        "ispinsInfo": {
            "options": [
                {
                    "buff": 1518,
                    "explain": "공격 시 MP 2000 감소\n\n현재 MP 2% 마다 피해 증가 +1876",
                    "explainDetail": "공격 시 MP 2000 감소 (쿨타임 1초)\n\n현재 MP 2% 마다 피해 증가 +1876 (최대 5중첩)"
                }
            ]
        }
    }
},
"trueDragon": {
    "rings": {
        "itemId": "6255f92b7b56a7ddd76f566a47ada800",
        "itemName": "진룡 : 무거운 철의 투지",
        "ispinsInfo": {
            "options": [
                {
                    "buff": 1405,
                    "explain": "공격 시 충격파 발생\n충격파에 5회 피격된 적 공격 시 적을 기절 상태로 만들며 무력화 게이지 1.5 감소\n\n기절 상태의 적 3회 공격 시 기절 지속 시간 3초 증가\n\n무력화 게이지가 파괴된 적이 존재할 때 피해 증가 +782",
                    "explainDetail": "공격 시 충격파 발생 (쿨타임 0.5초, 적의 방어력과 상관없이 총 피해 증가 수치의 30%만큼 피해를 줌)\n- 충격파 발생 시 20초 동안 피해 증가 +6252 (최대 1중첩)\n충격파에 5회 피격된 적 공격 시 적을 기절 상태로 만들며 무력화 게이지 1.5 감소 (쿨타임 8초)\n\n기절 상태의 적 3회 공격 시 기절 지속 시간 3초 증가 (쿨타임 5초)\n\n무력화 게이지가 파괴된 적이 존재할 때 피해 증가 +782"
                }
            ]
        }
    },
    "neck": {
        "itemId": "cc64795c07f57cb9e52967063276f795",
        "itemName": "진룡 : 압도하는 힘의 원천",
        "ispinsInfo": {
            "options": [
                {
                    "buff": 1405,
                    "explain": "공격 시 충격파 발생\n\n적의 무력화 게이지가 10% 감소될 때마다 피해 증가 +156",
                    "explainDetail": "공격 시 충격파 발생 (쿨타임 0.5초, 적의 방어력과 상관없이 총 피해 증가 수치의 40%만큼 피해를 줌)\n- 충격파 발생 시 20초 동안 피해 증가 +7037 (최대 1중첩)\n\n적의 무력화 게이지가 10% 감소될 때마다 피해 증가 +156 (최대 10중첩)\n- 적의 무력화 게이지가 재활성화 시 30초 동안 효과 유지"
                }
            ]
        }
    },
    "armlet": {
        "itemId": "568018f4d9ed013f352d412331ab67ba",
        "itemName": "진룡 : 잔혹한 용의 발톱",
        "ispinsInfo": {
            "options": [
                {
                    "buff": 1063,
                    "explain": "공격 시 충격파가 발생하며 적 무력화 게이지 0.05 감소\n\n충격파 발생 시 30초 동안 피해 증가 +208",
                    "explainDetail": "공격 시 충격파가 발생하며 적 무력화 게이지 0.05 감소 (쿨타임 0.1초, 적의 방어력과 상관없이 총 피해 증가 수치의 6%만큼 피해를 줌)\n- 충격파 쿨타임이 회복된 후 0.1초마다 기운이 충전됨 (최대 9회 충전)\n- 충전 후 공격 시 더 큰 충격파가 발생하며 1충전마다 무력화 게이지 감소량 및 충격파 피해량 100% 증가\n\n충격파 발생 시 30초 동안 피해 증가 +208 (최대 30중첩)\n- 충격파 1충전마다 피해 증가 버프 중첩 수 1 추가 증가"
                }
            ]
        }
    }
},
"fleamDragon": {
    "rings": {
        "itemId": "73f46c965770a5680576ad52219da4a5",
        "itemName": "화룡 : 끓어오르는 용의 숨결",
        "ispinsInfo": {
            "options": [
                {
                    "buff": 1405,
                    "explain": "공격 시 화룡의 기운 5 획득\n\n화룡의 기운 획득 시 10초동안 피해 증가 +6252",
                    "explainDetail": "공격 시 화룡의 기운 5 획득 (쿨타임 1초, 화룡의 기운 최대 44)\n\n화룡의 기운 획득 시 10초동안 피해 증가 +6252 (최대 1중첩)"
                }
            ]
        }
    },
    "neck": {
        "itemId": "6f388dd09d7149044abfd92fed63b4a6",
        "itemName": "화룡 : 타오르는 불의 분노",
        "ispinsInfo": {
            "options": [
                {
                    "buff": 1405,
                    "explain": "공격 시 화룡의 기운 4 획득\n화룡의 기운 획득 시 10초 동안 피해 증가 +3126\n\n커맨드 입력(←→+[장비 옵션 조작키]) 시 화룡의 분노 버프가 발동",
                    "explainDetail": "공격 시 화룡의 기운 4 획득 (쿨타임 1초, 화룡의 기운 최대 44)\n화룡의 기운 획득 시 10초 동안 피해 증가 +3126 (최대 1중첩, 화룡의 분노 버프가 적용 중일 때에는 피해 증가 적용되지 않음)\n\n커맨드 입력(←→+[장비 옵션 조작키]) 시 화룡의 분노 버프가 발동하여 아래의 효과 적용 (쿨타임 10초)\n- 화룡의 분노 버프 발동 시 분노한 화룡의 기운 44 획득\n- 화룡의 기운 획득 시 분노한 화룡의 기운으로 획득\n- 분노한 화룡의 기운이 44일 때 무색 큐브 조각을 소모하는 스킬 시전 시 폭주 버프가 발동하여 7초동안 스킬 공격력 10% 증가\n- 스킬 쿨타임 20% 증가\n- 커맨드 재입력 시 화룡의 분노 버프를 해제하며 화룡의 기운 44 획득\n\n(일반 [장비 옵션 조작키] 옵션 장비와 동시 착용 후 커맨드 입력 시, 융합된 장비의 [장비 옵션 조작키] 우선 사용)"
                }
            ]
        }
    },
    "armlet": {
        "itemId": "0e79738a52d19e87cf910fc16537887b",
        "itemName": "화룡 : 폭발하는 힘의 근원",
        "ispinsInfo": {
            "options": [
                {
                    "buff": 1177,
                    "explain": "공격 시 화룡의 기운 2 획득\n던전 입장 시 화룡의 기운 44 획득\n\n화룡의 기운이 44일 때 모든 기운을 소모하여 10초 동안 스킬 쿨타임 12% 감소\n화룡의 분노 버프 발동 중 피해 증가 +3126",
                    "explainDetail": "공격 시 화룡의 기운 2 획득 (쿨타임 1초, 화룡의 기운 최대 44)\n던전 입장 시 화룡의 기운 44 획득\n\n화룡의 기운이 44일 때 모든 기운을 소모하여 10초 동안 스킬 쿨타임 12% 감소 (최대 1중첩, 각성기 제외, 화룡의 분노 버프 발동 시 해제)\n화룡의 분노 버프 발동 중 피해 증가 +3126"
                }
            ]
        }
    }
}}